mlbaklava/__init__.py
mlbaklava/__version.py
mlbaklava/api.py
mlbaklava/commands.py
mlbaklava/distribution.py
mlbaklava/entrypoint.py
mlbaklava/environment.py
mlbaklava/images.py
mlbaklava/pypi.py
mlbaklava/render.py
mlbaklava/resources/__init__.py
mlbaklava/resources/deploy/Dockerfile
mlbaklava/resources/deploy/main.py
mlbaklava/resources/deploy/nginx.conf
mlbaklava/resources/process/Dockerfile
mlbaklava/resources/process/main.py
mlbaklava/resources/train/Dockerfile
mlbaklava/resources/train/main.py
mlbaklava-0.0.5.dev1.dist-info/LICENSE.md
mlbaklava-0.0.5.dev1.dist-info/METADATA
mlbaklava-0.0.5.dev1.dist-info/WHEEL
mlbaklava-0.0.5.dev1.dist-info/entry_points.txt
mlbaklava-0.0.5.dev1.dist-info/top_level.txt
mlbaklava-0.0.5.dev1.dist-info/RECORD
